README
setup.py
jazz/__init__.py
jazz.egg-info/PKG-INFO
jazz.egg-info/SOURCES.txt
jazz.egg-info/dependency_links.txt
jazz.egg-info/not-zip-safe
jazz.egg-info/requires.txt
jazz.egg-info/top_level.txt
jazz/database/GetQuery.py
jazz/database/ImportQuery.py
jazz/database/__init__.py
jazz/manufacture/Lot.py
jazz/manufacture/__init__.py
jazz/manufacture/lot.py
jazz/math/Geometry.py
jazz/math/__init__.py
jazz/sample/__init__.py
jazz/sample/sample.py
jazz/statsmod/Geometry.py
jazz/statsmod/HypoTests.py
jazz/statsmod/__init__.py
jazz/statsmod/vif.py
jazz/tests/__init__.py
jazz/tests/test.py